{
  "session_id": "integration_demo_1_1754005850",
  "start_time": "2025-07-31T16:50:50.868788",
  "end_time": "2025-07-31T16:50:50.869183",
  "character_name": "IntegrationDemo1",
  "character_level": null,
  "profession": null,
  "location": null,
  "total_xp_gained": 200,
  "total_credits_gained": 0,
  "total_deaths": 0,
  "total_quests_completed": 1,
  "total_combat_actions": 1,
  "total_travel_events": 0,
  "total_errors": 0,
  "average_combat_duration": 0.0,
  "success_rate": 0.0,
  "efficiency_score": 0.094,
  "session_goals": null,
  "session_mode": null,
  "notes": null,
  "events": [
    {
      "event_type": "xp_gain",
      "timestamp": "2025-07-31T16:50:50.869087",
      "description": "Gained 200 XP from quest_completion",
      "location": null,
      "coordinates": null,
      "metadata": {
        "source": "quest_completion"
      },
      "success": null,
      "error_message": null,
      "duration": null,
      "xp_gained": 200,
      "credits_gained": null,
      "items_gained": null,
      "items_lost": null
    }
  ],
  "combat_events": [
    {
      "combat_type": "attack",
      "target_name": "Enemy1",
      "damage_dealt": null,
      "damage_received": null,
      "ability_used": null,
      "weapon_used": null,
      "combat_duration": null,
      "victory": true,
      "loot_gained": null,
      "xp_gained": null,
      "location": null,
      "coordinates": null
    }
  ],
  "quest_events": [
    {
      "quest_name": "Quest 1",
      "quest_id": null,
      "status": "completed",
      "npc_name": null,
      "location": null,
      "objectives_completed": null,
      "rewards_gained": null,
      "xp_reward": 200,
      "credit_reward": null,
      "time_spent": null,
      "difficulty": null
    }
  ]
}