{
  "session_info": {
    "start_time": "2025-08-04T10:58:00.889654",
    "end_time": "2025-08-04T10:58:00.891787",
    "duration_minutes": 3.566666666666667e-05,
    "total_loot": 11,
    "target_items_found": [
      "Rare Crystal",
      "Ancient Artifact",
      "Precious Gem",
      "Legendary Weapon"
    ],
    "enemies_defeated": 0,
    "zones_visited": []
  },
  "loot_log": [
    {
      "time": "2025-08-04T10:58:00.890736",
      "item": "Gold Coin",
      "zone": null,
      "coordinates": null
    },
    {
      "time": "2025-08-04T10:58:00.890758",
      "item": "Health Potion",
      "zone": null,
      "coordinates": null
    },
    {
      "time": "2025-08-04T10:58:00.890766",
      "item": "Rare Crystal",
      "zone": null,
      "coordinates": null
    },
    {
      "time": "2025-08-04T10:58:00.890963",
      "item": "Magic Scroll",
      "zone": null,
      "coordinates": null
    },
    {
      "time": "2025-08-04T10:58:00.890974",
      "item": "Ancient Artifact",
      "zone": null,
      "coordinates": null
    },
    {
      "time": "2025-08-04T10:58:00.891144",
      "item": "Precious Gem",
      "zone": null,
      "coordinates": null
    },
    {
      "time": "2025-08-04T10:58:00.891155",
      "item": "Valuable Scroll",
      "zone": null,
      "coordinates": null
    },
    {
      "time": "2025-08-04T10:58:00.891303",
      "item": "Legendary Weapon",
      "zone": null,
      "coordinates": null
    },
    {
      "time": "2025-08-04T10:58:00.891313",
      "item": "Masterwork Armor",
      "zone": null,
      "coordinates": null
    },
    {
      "time": "2025-08-04T10:58:00.891478",
      "item": "Common Item",
      "zone": null,
      "coordinates": null
    },
    {
      "time": "2025-08-04T10:58:00.891507",
      "item": "Another Common Item",
      "zone": null,
      "coordinates": null
    }
  ],
  "combat_log": []
}