{
  "todos": {
    "todo_1": {
      "id": "todo_1",
      "title": "Complete Tatooine Trade Route",
      "description": "Finish the trade route quest for XP and credits",
      "category": "quest",
      "priority": "medium",
      "status": "not_started",
      "quest_id": null,
      "planet": "tatooine",
      "prerequisites": [],
      "rewards": {},
      "created_date": "2025-07-31T17:02:54.551927",
      "due_date": null,
      "completed_date": null,
      "notes": null,
      "tags": [
        "quest",
        "tatooine"
      ],
      "estimated_time": 30
    },
    "todo_2": {
      "id": "todo_2",
      "title": "Collect 100 Credits",
      "description": "Save up credits for better equipment",
      "category": "collection",
      "priority": "low",
      "status": "not_started",
      "quest_id": null,
      "planet": null,
      "prerequisites": [],
      "rewards": {},
      "created_date": "2025-07-31T17:02:54.552350",
      "due_date": null,
      "completed_date": null,
      "notes": null,
      "tags": [
        "credits",
        "saving"
      ],
      "estimated_time": 60
    },
    "todo_3": {
      "id": "todo_3",
      "title": "Visit All Planets",
      "description": "Travel to each planet to unlock new content",
      "category": "exploration",
      "priority": "high",
      "status": "not_started",
      "quest_id": null,
      "planet": null,
      "prerequisites": [],
      "rewards": {},
      "created_date": "2025-07-31T17:02:54.552815",
      "due_date": null,
      "completed_date": null,
      "notes": null,
      "tags": [
        "exploration",
        "travel"
      ],
      "estimated_time": 120
    },
    "todo_4": {
      "id": "todo_4",
      "title": "Complete Tatooine Trade Route",
      "description": "Finish the trade route quest for XP and credits",
      "category": "quest",
      "priority": "medium",
      "status": "not_started",
      "quest_id": null,
      "planet": "tatooine",
      "prerequisites": [],
      "rewards": {},
      "created_date": "2025-07-31T17:02:54.585571",
      "due_date": null,
      "completed_date": null,
      "notes": null,
      "tags": [
        "quest",
        "tatooine"
      ],
      "estimated_time": 30
    },
    "todo_5": {
      "id": "todo_5",
      "title": "Collect 100 Credits",
      "description": "Save up credits for better equipment",
      "category": "collection",
      "priority": "low",
      "status": "not_started",
      "quest_id": null,
      "planet": null,
      "prerequisites": [],
      "rewards": {},
      "created_date": "2025-07-31T17:02:54.586056",
      "due_date": null,
      "completed_date": null,
      "notes": null,
      "tags": [
        "credits",
        "saving"
      ],
      "estimated_time": 60
    },
    "todo_6": {
      "id": "todo_6",
      "title": "Visit All Planets",
      "description": "Travel to each planet to unlock new content",
      "category": "exploration",
      "priority": "high",
      "status": "not_started",
      "quest_id": null,
      "planet": null,
      "prerequisites": [],
      "rewards": {},
      "created_date": "2025-07-31T17:02:54.586483",
      "due_date": null,
      "completed_date": null,
      "notes": null,
      "tags": [
        "exploration",
        "travel"
      ],
      "estimated_time": 120
    },
    "todo_7": {
      "id": "todo_7",
      "title": "Complete Tatooine Trade Route",
      "description": "Finish the trade route quest for XP and credits",
      "category": "quest",
      "priority": "medium",
      "status": "not_started",
      "quest_id": null,
      "planet": "tatooine",
      "prerequisites": [],
      "rewards": {},
      "created_date": "2025-07-31T17:03:24.792052",
      "due_date": null,
      "completed_date": null,
      "notes": null,
      "tags": [
        "quest",
        "tatooine"
      ],
      "estimated_time": 30
    },
    "todo_8": {
      "id": "todo_8",
      "title": "Collect 100 Credits",
      "description": "Save up credits for better equipment",
      "category": "collection",
      "priority": "low",
      "status": "not_started",
      "quest_id": null,
      "planet": null,
      "prerequisites": [],
      "rewards": {},
      "created_date": "2025-07-31T17:03:24.792678",
      "due_date": null,
      "completed_date": null,
      "notes": null,
      "tags": [
        "credits",
        "saving"
      ],
      "estimated_time": 60
    },
    "todo_9": {
      "id": "todo_9",
      "title": "Visit All Planets",
      "description": "Travel to each planet to unlock new content",
      "category": "exploration",
      "priority": "high",
      "status": "not_started",
      "quest_id": null,
      "planet": null,
      "prerequisites": [],
      "rewards": {},
      "created_date": "2025-07-31T17:03:24.793196",
      "due_date": null,
      "completed_date": null,
      "notes": null,
      "tags": [
        "exploration",
        "travel"
      ],
      "estimated_time": 120
    },
    "todo_10": {
      "id": "todo_10",
      "title": "Complete Tatooine Trade Route",
      "description": "Finish the trade route quest for XP and credits",
      "category": "quest",
      "priority": "medium",
      "status": "not_started",
      "quest_id": null,
      "planet": "tatooine",
      "prerequisites": [],
      "rewards": {},
      "created_date": "2025-07-31T17:03:24.827523",
      "due_date": null,
      "completed_date": null,
      "notes": null,
      "tags": [
        "quest",
        "tatooine"
      ],
      "estimated_time": 30
    },
    "todo_11": {
      "id": "todo_11",
      "title": "Collect 100 Credits",
      "description": "Save up credits for better equipment",
      "category": "collection",
      "priority": "low",
      "status": "not_started",
      "quest_id": null,
      "planet": null,
      "prerequisites": [],
      "rewards": {},
      "created_date": "2025-07-31T17:03:24.828124",
      "due_date": null,
      "completed_date": null,
      "notes": null,
      "tags": [
        "credits",
        "saving"
      ],
      "estimated_time": 60
    },
    "todo_12": {
      "id": "todo_12",
      "title": "Visit All Planets",
      "description": "Travel to each planet to unlock new content",
      "category": "exploration",
      "priority": "high",
      "status": "not_started",
      "quest_id": null,
      "planet": null,
      "prerequisites": [],
      "rewards": {},
      "created_date": "2025-07-31T17:03:24.828625",
      "due_date": null,
      "completed_date": null,
      "notes": null,
      "tags": [
        "exploration",
        "travel"
      ],
      "estimated_time": 120
    },
    "todo_13": {
      "id": "todo_13",
      "title": "Complete Quest 1",
      "description": null,
      "category": "quest",
      "priority": "high",
      "status": "not_started",
      "quest_id": null,
      "planet": null,
      "prerequisites": [],
      "rewards": {},
      "created_date": "2025-07-31T17:03:29.084555",
      "due_date": null,
      "completed_date": null,
      "notes": null,
      "tags": [],
      "estimated_time": null
    },
    "todo_14": {
      "id": "todo_14",
      "title": "Complete Tatooine Trade Route",
      "description": "Finish the trade route quest for XP and credits",
      "category": "quest",
      "priority": "medium",
      "status": "not_started",
      "quest_id": null,
      "planet": "tatooine",
      "prerequisites": [],
      "rewards": {},
      "created_date": "2025-07-31T17:05:52.575670",
      "due_date": null,
      "completed_date": null,
      "notes": null,
      "tags": [
        "quest",
        "tatooine"
      ],
      "estimated_time": 30
    },
    "todo_15": {
      "id": "todo_15",
      "title": "Collect 100 Credits",
      "description": "Save up credits for better equipment",
      "category": "collection",
      "priority": "low",
      "status": "not_started",
      "quest_id": null,
      "planet": null,
      "prerequisites": [],
      "rewards": {},
      "created_date": "2025-07-31T17:05:52.576281",
      "due_date": null,
      "completed_date": null,
      "notes": null,
      "tags": [
        "credits",
        "saving"
      ],
      "estimated_time": 60
    },
    "todo_16": {
      "id": "todo_16",
      "title": "Visit All Planets",
      "description": "Travel to each planet to unlock new content",
      "category": "exploration",
      "priority": "high",
      "status": "not_started",
      "quest_id": null,
      "planet": null,
      "prerequisites": [],
      "rewards": {},
      "created_date": "2025-07-31T17:05:52.576815",
      "due_date": null,
      "completed_date": null,
      "notes": null,
      "tags": [
        "exploration",
        "travel"
      ],
      "estimated_time": 120
    },
    "todo_17": {
      "id": "todo_17",
      "title": "Complete Tatooine Trade Route",
      "description": "Finish the trade route quest for XP and credits",
      "category": "quest",
      "priority": "medium",
      "status": "not_started",
      "quest_id": null,
      "planet": "tatooine",
      "prerequisites": [],
      "rewards": {},
      "created_date": "2025-07-31T17:05:52.617153",
      "due_date": null,
      "completed_date": null,
      "notes": null,
      "tags": [
        "quest",
        "tatooine"
      ],
      "estimated_time": 30
    },
    "todo_18": {
      "id": "todo_18",
      "title": "Collect 100 Credits",
      "description": "Save up credits for better equipment",
      "category": "collection",
      "priority": "low",
      "status": "not_started",
      "quest_id": null,
      "planet": null,
      "prerequisites": [],
      "rewards": {},
      "created_date": "2025-07-31T17:05:52.617888",
      "due_date": null,
      "completed_date": null,
      "notes": null,
      "tags": [
        "credits",
        "saving"
      ],
      "estimated_time": 60
    },
    "todo_19": {
      "id": "todo_19",
      "title": "Visit All Planets",
      "description": "Travel to each planet to unlock new content",
      "category": "exploration",
      "priority": "high",
      "status": "not_started",
      "quest_id": null,
      "planet": null,
      "prerequisites": [],
      "rewards": {},
      "created_date": "2025-07-31T17:05:52.618500",
      "due_date": null,
      "completed_date": null,
      "notes": null,
      "tags": [
        "exploration",
        "travel"
      ],
      "estimated_time": 120
    },
    "todo_20": {
      "id": "todo_20",
      "title": "Complete Quest 1",
      "description": null,
      "category": "quest",
      "priority": "high",
      "status": "not_started",
      "quest_id": null,
      "planet": null,
      "prerequisites": [],
      "rewards": {},
      "created_date": "2025-07-31T17:05:56.029724",
      "due_date": null,
      "completed_date": null,
      "notes": null,
      "tags": [],
      "estimated_time": null
    },
    "todo_21": {
      "id": "todo_21",
      "title": "Complete Quest 1",
      "description": null,
      "category": "quest",
      "priority": "high",
      "status": "not_started",
      "quest_id": null,
      "planet": null,
      "prerequisites": [],
      "rewards": {},
      "created_date": "2025-07-31T17:06:31.713887",
      "due_date": null,
      "completed_date": null,
      "notes": null,
      "tags": [],
      "estimated_time": null
    }
  },
  "last_updated": "2025-07-31T17:06:31.714006"
}